{
    "titleMainWindow": "Trigger Craft 触发工坊",
    "menuFile": "文件",
    "menuNew": "新建",
    "menuOpen": "打开...",
    "menuReload": "重新打开",
    "menuSave": "保存",
    "menuSaveAs": "另存为...",
    "menuClose": "关闭",
    "menuExit": "退出",
    "menuEdit": "编辑",
    "menuExportAllTriggerToText": "导出所有触发为文本...",
    "menuImportAllTriggerFromText": "从文本还原触发...",
    "menuExportTriggerToText": "导出选择触发为文本...",
    "menuImportTriggerFromText": "从文本添加触发...",
    "menuExportAllText": "导出所有触发文本...",
    "menuImportText": "导入触发文本...",
    "menuLanguage": "语言",
    "menuHelp": "帮助",
    "menuLogs": "显示日志...",
    "menuHomePage": "Github 页面",
    "menuAbout": "关于...",
    "menuDuplicateIncludeSource": "转换起始玩家",
    "menuDuplicateIncludeTarget": "转换目标玩家",
    "menuDuplicateIncludeStrict": "仅转换对应玩家",
    "menuDuplicateAddDuplicateMark": "复制时添加标记",
    "menuDuplicateDuplicateAllMarked": "复制已标记的原始触发...",
    "menuDuplicateAdvanced": "高级...",
    "menuDeduplicateAllMarked": "移除已标记的衍生触发...",
    "menuDeduplicateAdvanced": "高级...",
    "menuReorderCEs": "重排条件和效果...",
    "titleLogs": "日志",
    "btnClearLogs": "清空",
    "titleAbout": "关于 触发工坊(Trigger Craft)",
    "textAboutTitle": "触发工坊(Trigger Craft)",
    "textAbout": "作者：夜游神",
    "textAboutRelease": "版本: {0}",
    "textAboutPoweredBy": "powered by AoE2ScenarioParser",
    "titleSelectScenario": "打开",
    "typeNameScenario": "帝国时代 II 决定版场景文件",
    "typeNameAll": "所有文件",
    "titleOpenfailed": "打开失败",
    "messageOpenfailed": "无法读取场景，原因：\n{0}",
    "messageOpenfailedByEarlyVersion": "场景文件版本是 {0}，但该版本触发工坊仅支持 {1}，\n请使用最新版游戏本体保存场景。",
    "messageOpenfailedByNewerVersion": "场景文件版本是 {0}，但该版本触发工坊仅支持 {1}，\n请关注更新。",
    "messageOpenfailedByEarlyTrigger": "场景文件版本是 {0}，但触发器版本为 {1}，\n请使用最新版游戏本体保存场景。",
    "titleError": "错误",
    "messageError": "发生错误：\n{0}",
    "messageValueRangeInvalid": "范围格式无效：\n{0}",
    "messageJsonDecodeError": "无法解析为 JSON 文件。",
    "messageJsonSchemaError": "JSON 格式不符合要求。",
    "messageJsonNotRestorableError": "无法从不完整的触发列表中还原。",
    "titleSavefailed": "保存失败",
    "messageSavefailed": "无法保存场景，原因：\n{0}",
    "messageSavefailedByBadInteger": "一个或多个整型变量超出场景格式范围。",
    "messageTitleWarning": "警告",
    "messageWarningDeduplicateNotMatch": "选中的项目与下方的项目并不相似，\n\n确定要继续吗？",
    "titleSelectSaveScenario": "另存为",
    "titleAskSaveScenario": "保存",
    "messageAskSaveScenario": "是否要保存当前场景？",
    "titleSelectTriggerJson": "打开",
    "titleSelectSaveTriggerJson": "打开",
    "tabTriggerEditor": "触发",
    "tabUnitEditor": "单位",
    "tabMapView": "地图视图",
    "tabMetaView": "场景信息",
    "tabTriggerInfo": "触发信息",
    "tabConditionInfo": "条件信息",
    "tabEffectInfo": "效果信息",
    "tabUnitInfo": "单位信息",
    "tooltipAddTrigger": "新建触发",
    "tooltipAddCondition": "新建条件",
    "tooltipAddEffect": "新建效果",
    "tooltipDeleteItem": "删除节点",
    "tooltipDuplicateItem": "创建副本",
    "tooltipDuplicateItemForAll": "复制到所有玩家",
    "tooltipUnduplicateItemForAll": "为其他玩家删除",
    "tooltipMoveItemUp": "上移",
    "tooltipMoveItemDown": "下移",
    "tooltipSortTriggers": "按显示顺序重排触发",
    "tooltipDuplicateMultipleForAll": "复制到所有玩家(范围)",
    "tooltipUnduplicateMultipleForAll": "为其他玩家删除(范围)",
    "tooltipDeleteMultiple": "删除触发(范围)",
    "tooltipMoveMultipleTo": "移动到指定触发前(范围)",
    "tooltipSetLocationUnit": "从单位列表采取",
    "tooltipSetLocationArea": "从地图视图采取",
    "tooltipMapView": "纵向导览: 滚轮 | 横向导览: Shift + 滚轮 | 缩放: Ctrl + 滚轮 | 选取单元格: 鼠标左键 | 选取区域: Shift + 鼠标左键 | 取消: 鼠标右键",
    "labelFrom": "从",
    "labelTo": "到",
    "labelTriggerList": "触发列表",
    "labelTriggerName": "触发名称",
    "formatNewTriggerName": "新触发 {0}",
    "formatDuplicatedTriggerName": "{0} - 副本",
    "labelScenVersion": "格式版本：",
    "labelScenAuthor": "作者：",
    "labelScenSaveDate": "上次保存：",
    "labelScenTriggerVersion": "触发格式版本：",
    "labelMsgStringTableId": "字符串表 ID：",
    "messageNames": {
        "instructions": "场景指南",
        "hints": "提示",
        "scouts": "侦察",
        "victory": "胜利",
        "loss": "失败",
        "history": "历史"
    },
    "labelPoint1": "区格 A",
    "labelPoint2": "区格 B",
    "labelRealArea": "实际区域",
    "btnTriggerEnable": "启用",
    "btnTriggerLoop": "循环",
    "btnTriggerExecuteOnLoad": "加载时执行",
    "labelTriggerDescriptionOrder": "描述顺序",
    "labelTriggerDescription": "描述",
    "labelTriggerShortDescription": "简短描述",
    "btnTriggerAsObjective": "显示任务",
    "btnTriggerOnScreen": "在屏幕上显示",
    "labelTriggerDescriptionStringTableID": "字符串表ID",
    "labelTriggerShortDescriptionStringTableID": "字符串表ID",
    "btnTriggerMakeHeader": "设为标题",
    "btnTriggerMuteObjective": "静音任务",
    "labelNotSupportYet": "暂不支持",
    "comboValueNone": "<无>",
    "comboValueAllPlayer": "所有玩家",
    "comboValueFullMap": "全图",
    "comboValueSelectedArea": "所选区域",
    "labelUnitList": "单位列表",
    "labelUnitConst": "单位类型",
    "labelUnitPlayer": "玩家",
    "labelUnitGarrison": "驻扎于",
    "labelUnitLocation": "位置 (x,y)",
    "labelUnitZLocation": "位置 z",
    "labelUnitRotation": "旋转/朝向",
    "labelUnitInitialFrame": "起始帧",
    "labelUnitStatus": "状态",
    "labelUnitReferenceId": "单位 ID",
    "labelUnitCaptionStringID": "标题字符串表 ID",
    "labelUnitCaption": "标题",
    "titleUnitConst": "单位类型",
    "btnCancel": "取消",
    "btnConfirm": "确认",
    "comboValueEffectInstructionPanelPosition": "位置{0}",
    "noticeScenarioLoading": "场景加载中...",
    "noticeScenarioLoaded": "场景已加载。",
    "noticeScenarioSaved": "场景已保存。",
    "noticeTriggerJsonSaved": "已导出触发 JSON.",
    "noticeTriggerJsonRestored": "已从 JSON 还原触发。",
    "noticeTriggerJsonAdded": "已从 JSON 添加触发。",
    "noticeDuplicateCompleted": "已完成复制。",
    "noticeDeduplicateCompleted": "已从其他玩家删除。",
    "noticeDeleteDuplicateCompleted": "已完成删除。",
    "noticeNotEnoughTriggersToDelete": "错误：剩余触发数过少",
    "noticeNotEnoughConditionsToDelete": "错误：剩余条件数过少",
    "noticeNotEnoughEffectsToDelete": "错误：剩余效果数过少",
    "noticeSortCompleted": "已完成重排序。",
    "noticeFormatValueRangeInvalid": "范围格式无效: {0}",
    "noticeValueRangeErrMsgValueMissing": "缺少数值",
    "noticeValueRangeErrMsgFrontLargerThanBack": "起始ID大于结束ID",
    "noticeValueRangeErrMsgFrontLargerThanTotal": "起始ID大于总数",
    "noticeValueRangeErrMsgMustBeMultiple": "该操作的范围必须是玩家数量的倍数",
    "noticeValueRangeErrMsgTargetMissing": "缺少目标ID",
    "noticeValueRangeErrMsgTargetInRange": "目标ID在范围内",
    "noticeFormatAspLoadingSection": "载入{0}...",
    "noticeValueAspSectionName": {
        "FileHeader": "文件头",
        "DataHeader": "数据头",
        "Messages": "信息",
        "Cinematics": "过场动画",
        "BackgroundImage": "背景图像",
        "PlayerDataTwo": "补充玩家数据",
        "GlobalVictory": "全体胜利",
        "Diplomacy": "外交",
        "Options": "选项",
        "Map": "地形",
        "Units": "单位",
        "Triggers": "触发",
        "Files": "附件"
    },
    "conditionAttributeName": {
        "condition_type": "条件类型",
        "quantity": "数量",
        "attribute": "属性",
        "unit_object": "目标",
        "next_object": "下一个目标",
        "object_list": "单位种类",
        "source_player": "起始玩家",
        "technology": "科技",
        "timer": "定时器",
        "trigger_id": "触发器列表",
        "area": "设定区域",
        "area_x1": "Area X1",
        "area_y1": "Area Y1",
        "area_x2": "Area X2",
        "area_y2": "Area Y2",
        "object_group": "物体种属",
        "object_type": "物体类型",
        "ai_signal": "AI 信号",
        "inverted": "条件反转",
        "variable": "变量",
        "comparison": "比较",
        "target_player": "目标玩家",
        "unit_ai_action": "行动类型",
        "object_state": "物体状态",
        "timer_id": "定时器 ID",
        "victory_timer_type": "胜利定时器",
        "include_changeable_weapon_objects": "含可变武器单位",
        "decision_id": "决定 ID",
        "decision_option": "决定选项",
        "variable2": "变量",
        "xs_function": "XS 脚本",
        "local_technology": "本地科技",
        "object_group2": "物体种属",
        "object_type2": "物体类型"
    },
    "conditionNameFormatForUnknown": "<条件: 未知 {0}>",
    "conditionName": {
        "0": "<条件: 无>",
        "1": "将物体带到指定区域",
        "2": "将物体带到指定物体",
        "3": "拥有物体",
        "4": "拥有物体少于",
        "5": "区域内的物体",
        "6": "消灭物体",
        "7": "捕获物体",
        "8": "堆积属性",
        "9": "研究科技",
        "10": "定时器",
        "11": "选择物体",
        "12": "AI 信号",
        "13": "玩家被击败",
        "14": "物体已有目标",
        "15": "物体可视",
        "16": "物体不可视",
        "17": "正研究科技",
        "18": "已驻扎单位",
        "19": "难度等级",
        "20": "概率",
        "21": "科技状态",
        "22": "变量值",
        "23": "物体生命值",
        "24": "外交状态",
        "25": "脚本调用",
        "26": "选择物体 (多人游戏)",
        "27": "物体可视 (多人游戏)",
        "28": "物体已行动",
        "29": "条件逻辑或",
        "30": "多人游戏 AI 信号",
        "54": "建筑贸易中",
        "55": "显示定时器已触发",
        "56": "胜利定时器",
        "57": "条件逻辑与",
        "75": "决定已触发",
        "76": "物体已攻击",
        "77": "英雄力量施放",
        "78": "比较变量",
        "79": "触发已激活",
        "80": "研究本地科技"
    },
    "fmtStringFullMap": "全图",
    "fmtStringAnyUnit": "单位",
    "fmtStringAreaUnitCombineFormat": "{0}{1}",
    "fmtStringPlayerUnitCombineFormat": "{0}{1}",
    "fmtStringStateUnitCombineFormat": "{0}{1}",
    "fmtStringIf": "若",
    "fmtStringNot": "非",
    "fmtStringPlayerN": "玩家{0}",
    "fmtStringGaia": "盖亚",
    "fmtStringIncludeCWO": "含可变武器",
    "conditionDescriptionFormat": {
        "0": "无",
        "1": "将{0}带到{1}",
        "2": "将{0}带给{1}",
        "3": "{0}拥有{1}{3}不少于{2}",
        "4": "区域{3}内{0}{1}{4}不多于{2}",
        "5": "区域{3}内{0}{4}{1}{5}不少于{2}",
        "6": "消灭{0}",
        "7": "{0}捕获{1}",
        "8": "{0}{1}不少于{2}",
        "9": "{0}已研究{1}",
        "10": "{0}秒后",
        "11": "选中{0}",
        "12": "AI 信号 {0}",
        "13": "{0}被击败",
        "14": "{0}已有目标{1}",
        "15": "{0}可视",
        "16": "{0}不可视",
        "17": "{0}正研究科技{1}",
        "18": "{0}驻扎单位不少于{1}",
        "19": "难度不大于{0}",
        "20": "{0}% 概率",
        "21": "{0}{2}科技{1}",
        "22": "变量{0}{2}{1}",
        "23": "{0}生命值{2}{1}",
        "24": "{0}对{1}{2}",
        "25": "脚本调用",
        "26": "{0}选中{1}(联机)",
        "27": "{1}对{0}可视(联机)",
        "28": "{0}已{2}{1}",
        "29": "  或",
        "30": "多人游戏 AI 信号 {0}",
        "54": "建筑{0}贸易中",
        "55": "显示定时器{0}已触发",
        "56": "{0}{1}{3}{2}",
        "57": "  且",
        "75": "决定{0}已触发({1})",
        "76": "{0}{1}已攻击{2}({3})",
        "77": "{0}施放英雄力量",
        "78": "变量{0}{2}变量{1}",
        "79": "已激活「{0}」"
    },
    "conditionDescriptionInvertFormat": {
        "1": "未将{0}带到{1}",
        "2": "未将{0}带给{1}",
        "5": "区域{3}内{0}{4}{1}{5}少于{2}",
        "6": "{0}存在",
        "7": "{0}未捕获{1}",
        "8": "{0}{1}少于{2}",
        "9": "{0}未研究{1}",
        "10": "{0}秒内",
        "11": "未选中{0}",
        "12": "未发生 AI 信号 {0}",
        "13": "{0}未被击败",
        "14": "{0}未有目标{1}",
        "17": "{0}未在研究科技{1}",
        "18": "{0}驻扎单位少于{1}",
        "19": "难度大于{0}",
        "21": "{0}未{2}科技{1}",
        "22": "变量{0}未{2}{1}",
        "23": "{0}生命值未{2}{1}",
        "24": "{0}未对{1}{2}",
        "26": "{0}未选中{1}(联机)",
        "27": "{1}未对{0}可视(联机)",
        "28": "{0}未{2}{1}",
        "30": "多人游戏未发生 AI 信号 {0}",
        "54": "建筑{0}未在贸易",
        "55": "显示定时器{0}未触发",
        "56": "{0}{1}未{3}{2}",
        "75": "决定{0}未触发({1})",
        "76": "{0}{1}未攻击{2}({3})",
        "78": "变量{0}未{2}变量{1}",
        "79": "未激活「{0}」"
    },
    "effectAttributeName": {
        "effect_type": "效果类型",
        "ai_script_goal": "AI 脚本目标",
        "armour_attack_quantity": "攻击/护甲值",
        "armour_attack_class": "护甲类型",
        "quantity": "数量",
        "tribute_list": "贡品列表",
        "diplomacy": "外交状态",
        "object_list_unit_id": "单位种类",
        "source_player": "起始玩家",
        "target_player": "目标玩家",
        "technology": "科技",
        "string_id": "字符串表 ID",
        "display_time": "定时器",
        "trigger_id": "触发器列表",
        "location": "设定位置",
        "location_x": "Location X",
        "location_y": "Location Y",
        "location_object_reference": "Location Object",
        "area": "设定区域",
        "area_x1": "Area X1",
        "area_y1": "Area Y1",
        "area_x2": "Area X2",
        "area_y2": "Area Y2",
        "object_group": "物体种属",
        "object_type": "物体类型",
        "instruction_panel_position": "面板位置",
        "attack_stance": "物体姿态",
        "time_unit": "定时器单位",
        "enabled": "启用",
        "food": "",
        "wood": "",
        "stone": "",
        "gold": "",
        "item_id": "",
        "flash_object": "闪烁物体",
        "force_research_technology": "强制研究",
        "visibility_state": "可见度",
        "scroll": "滚动",
        "operation": "操作",
        "object_list_unit_id_2": "目标单位种类",
        "button_location": "按键位置",
        "ai_signal_value": "AI 信号",
        "object_attributes": "属性",
        "variable": "变量",
        "timer": "定时器",
        "facet": "朝向",
        "play_sound": "播放声音",
        "player_color": "颜色",
        "color_mood": "色调",
        "reset_timer": "复位定时器",
        "object_state": "物体状态",
        "action_type": "行动类型",
        "resource_1": "资源 1",
        "resource_1_quantity": "数量",
        "resource_2": "资源 2",
        "resource_2_quantity": "数量",
        "resource_3": "资源 3",
        "resource_3_quantity": "数量",
        "decision_id": "决定",
        "string_id_option1": "字符串表 ID",
        "string_id_option2": "字符串表 ID",
        "variable2": "变量",
        "message": "信息",
        "__variant_message": "文本",
        "sound_name": "声音 (事件) 名",
        "selected_object_ids": "设定物体",
        "message_option1": "选项 1",
        "message_option2": "选项 2",
        "max_units_affected": "最大生效单位数",
        "disable_garrison_unload_sound": "禁用驻扎卸载音效",
        "hotkey": "热键",
        "train_time": "训练时间",
        "local_technology": "本地科技",
        "disable_sound": "禁用音效",
        "object_group2": "物体种属",
        "object_type2": "物体类型",
        "quantity_float": "数量",
        "facet2": "朝向",
        "global_sound": "全局音效",
        "issue_group_command": "向阵形发出命令",
        "queue_action": "列队操作"
    },
    "effectNameFormatForUnknown": "<效果: 未知 {0}>",
    "effectName": {
        "0": "<效果: 无>",
        "1": "改变外交态度",
        "2": "研究科技",
        "3": "发送聊天",
        "4": "播放声音",
        "5": "贡品",
        "6": "开启城门",
        "7": "锁定城门",
        "8": "激活触发器",
        "9": "关闭触发器",
        "10": "AI 场景目标",
        "11": "创建物体",
        "12": "任务物体",
        "13": "宣布胜利",
        "14": "击杀物体",
        "15": "移除物体",
        "16": "改变视角",
        "17": "卸下",
        "18": "改变所有权",
        "19": "巡逻",
        "20": "显示指南",
        "21": "清除指南",
        "22": "冻结物体",
        "23": "启用高级按钮",
        "24": "损害物体",
        "25": "放置地基",
        "26": "改变物体名称",
        "27": "改变物体生命值",
        "28": "改变物体攻击力",
        "29": "停止物体",
        "30": "移动攻击",
        "31": "改变物体护甲",
        "32": "改变物体射程",
        "33": "改变物体速度",
        "34": "治疗物体",
        "35": "传送物体",
        "36": "改变物体姿态",
        "37": "显示定时器",
        "38": "启用/禁用物体",
        "39": "启用/禁用科技",
        "40": "改变物体费用",
        "41": "设置玩家能见度",
        "42": "改变物体图标",
        "43": "替换物体",
        "44": "改变物体描述",
        "45": "改变玩家名称",
        "46": "改变训练位置",
        "47": "改变科技位置",
        "48": "改变文明名称",
        "49": "创建驻扎物体",
        "50": "确认 AI 信号",
        "51": "修改属性",
        "52": "修改资源",
        "53": "根据变量修改资源",
        "54": "设定建筑聚集点",
        "55": "脚本调用",
        "56": "改变变量",
        "57": "移除定时器",
        "58": "改变物体玩家颜色",
        "59": "改变物体文明名称",
        "60": "改变物体玩家名称",
        "61": "禁用单位锁定",
        "62": "启用单位锁定",
        "63": "改变科技成本",
        "64": "改变科技研究时间",
        "65": "改变科技名称",
        "66": "改变科技描述",
        "67": "启用科技堆叠",
        "68": "禁用科技堆叠",
        "69": "确认多人游戏 AI 信号",
        "70": "禁用物体选择",
        "71": "启用物体选择",
        "72": "更改色调",
        "73": "启用物体删除",
        "74": "禁用物体删除",
        "75": "训练单位",
        "76": "开始研究",
        "77": "创建物体攻击力",
        "78": "创建物体护甲",
        "79": "根据变量修改属性",
        "80": "设置物体成本",
        "81": "加载键值",
        "82": "存储键值",
        "83": "删除键值",
        "84": "更改科技图标",
        "85": "更改科技热键",
        "86": "根据资源修改变量",
        "87": "根据属性修改变量",
        "88": "更改物体说明",
        "89": "更改玩家颜色",
        "90": "创建决定",
        "91": "成就触发器",
        "92": "珀斯教程触发器",
        "93": "创建 WS 提示",
        "94": "移除 WS 提示",
        "95": "创建战役目标",
        "96": "设置战役目标状态",
        "97": "打开战役目标对话框",
        "98": "禁用单位可攻击",
        "99": "启用单位可攻击",
        "100": "根据变量修改变量",
        "101": "将单位计入变量",
        "102": "添加训练位置",
        "103": "研究本地科技",
        "104": "修改种属属性",
        "105": "修改物体属性",
        "106": "根据变量修改物体属性",
        "107": "更改物体能见度"
    },
    "fmtMessageLengthLimit": 16,
    "fmtStringForceResearch": "强制",
    "fmtStringVictory": "胜利",
    "fmtStringDefeat": "失败",
    "fmtStringViewScroll": "移动",
    "fmtStringViewSwitch": "切换",
    "fmtStringFaceTo": "朝向{0}",
    "fmtStringAttackTypeCombine": "{0}类型攻击",
    "fmtStringArmorTypeCombine": "{0}类型护甲",
    "fmtEnable": "启用",
    "fmtDisable": "禁用",
    "fmtChangeViewTime": "{0}秒内",
    "fmtCostFree": "免费",
    "fmtUnlimitedTimes": "无限",
    "fmtTimerCreate": "创建",
    "fmtTimerReset": "重置",
    "effectDescriptionFormatShift": {
        "0": "无",
        "1": "令{0}对{1}闪烁",
        "2": "{0}的{1}的{2}{4}「{3}」"
    },
    "effectDescriptionFormat": {
        "0": "无",
        "1": "{0}对{1}{2}",
        "2": "{0}{2}研究{1}",
        "3": "向{0}发送「{1}」",
        "4": "向{0}在{1}播放「{2}」",
        "5": "{0}向{1}进贡{2}{3}",
        "6": "开启{0}",
        "7": "锁定{0}",
        "8": "激活「{0}」",
        "9": "关闭「{0}」",
        "10": "AI 场景目标 {0}",
        "11": "在{2}创建{0}的{1}{3}",
        "12": "令{0}对{1}进行{2}",
        "13": "宣布{0}{1}",
        "14": "击杀{0}",
        "15": "移除{0}",
        "16": "{3}{2}{0}视角到{1}",
        "17": "令{0}到{1}卸下",
        "18": "改变{0}所有权为{1}",
        "19": "令{0}巡逻至{1}",
        "20": "显示「{0}」",
        "21": "清除位置{0}的指南",
        "22": "冻结{0}",
        "23": "启用高级按钮",
        "24": "损害{0}的{1}生命",
        "25": "在{2}放置{0}的{1}地基",
        "26": "设{0}名称为「{1}」",
        "27": "{0}的生命值{2}{1}",
        "28": "{0}的{3}攻击{2}{1}",
        "29": "停止{0}",
        "30": "令{0}移动攻击至{1}",
        "31": "{0}的{3}护甲{2}{1}",
        "32": "{0}的射程{2}{1}",
        "33": "{0}的速度增加{1}%",
        "34": "治疗{0}的{1}生命",
        "35": "将{0}传送至{1}",
        "36": "设{0}为{1}",
        "37": "{3}{2}定时器{0}={1}「{4}」",
        "38": "{2}{0}的{1}",
        "39": "{2}{0}的{1}",
        "40": "设{0}的{1}费用为{2}",
        "41": "使{1}对{0}{2}",
        "42": "设{0}图标为{1}",
        "43": "将{0}替换为{1}的{2}",
        "44": "设{0}的{1}描述为{2}",
        "45": "设{0}名称为{1}",
        "46": "设{0}的{1}训练位置为{2}的{3}按钮",
        "47": "设{0}的{1}研究位置为{2}的{3}按钮",
        "48": "设{0}文明名称为{1}",
        "49": "在{0}创建{1}的驻扎{2}",
        "50": "响应 AI 信号 {0}",
        "51": "{0}的{1}的{2}{4}{3}",
        "52": "{0}的{1}{3}{2}",
        "53": "{0}的{1}{3}变量{2}",
        "54": "设{0}聚集点为{1}",
        "55": "脚本调用: {0}",
        "56": "变量{0}{2}{1}",
        "57": "移除定时器{0}",
        "58": "设{0}玩家颜色为{1}",
        "59": "设{0}文明名称为{1}",
        "60": "设{0}玩家名称为{1}",
        "61": "禁用{0}锁定",
        "62": "启用{0}锁定",
        "63": "设{0}的{1}研究费用为{2}",
        "64": "设{0}的{1}研究时间为{2}秒",
        "65": "设{0}的{1}科技名称为{2}",
        "66": "设{0}的{1}科技描述为{2}",
        "67": "允许堆叠{0}的{1}{2}次",
        "68": "禁止堆叠{0}的{1}",
        "69": "响应多人游戏 AI 信号 {0}",
        "70": "禁止选择{0}",
        "71": "允许选择{0}",
        "72": "{1}更改色调为{0}",
        "73": "允许删除{0}",
        "74": "禁止删除{0}",
        "75": "令{0}训练{1}到{2}",
        "76": "令{0}的{1}开始研究{2}",
        "77": "{0}创建{3}攻击{2}{1}",
        "78": "{0}创建{3}护甲{2}{1}",
        "79": "{0}的{1}的{2}{4}变量{3}",
        "80": "?设{0}的{1}费用为{2}{3}",
        "81": "加载键值",
        "82": "存储键值",
        "83": "删除键值",
        "84": "设{0}的{1}科技图标为{2}",
        "85": "设{0}的{1}科技热键为{2}",
        "86": "变量{0}{3}{1}的{2}",
        "87": "变量{0}{4}{1}的{2}的{3}",
        "88": "设{0}说明为{1}",
        "89": "设{0}颜色为{1}",
        "90": "创建决定",
        "91": "<成就触发器>",
        "92": "<珀斯教程触发器>",
        "93": "<创建 WS 提示>",
        "94": "<移除 WS 提示>",
        "95": "<创建战役目标>",
        "96": "<设置战役目标状态>",
        "97": "<打开战役目标对话框>",
        "98": "设{0}不可被攻击",
        "99": "设{0}可被攻击",
        "100": "变量{0}{2}变量{1}",
        "101": "变量{0}设为{1}的数量"
    },
    "datasetObjectClass": {
        "-1": "<无>",
        "0": "步弓手",
        "1": "古物",
        "2": "贸易艇",
        "3": "建筑",
        "4": "平民",
        "5": "海洋鱼群",
        "6": "步兵",
        "7": "浆果灌木丛",
        "8": "石矿",
        "9": "被捕食动物",
        "10": "捕食性动物",
        "11": "其他",
        "12": "骑兵",
        "13": "攻城武器",
        "14": "地形",
        "15": "树木",
        "16": "树桩",
        "17": "治疗者",
        "18": "僧侣",
        "19": "贸易车",
        "20": "运输船",
        "21": "捕鱼艇",
        "22": "战船",
        "23": "西班牙征服者",
        "24": "战象",
        "25": "英雄",
        "26": "骑象射手",
        "27": "城墙",
        "28": "方阵步兵",
        "29": "家畜",
        "30": "旗帜",
        "31": "深海鱼类",
        "32": "金矿",
        "33": "海滨鱼群",
        "34": "悬崖",
        "35": "爆破兵",
        "36": "骑射手",
        "37": "幽灵",
        "38": "鸟",
        "39": "城门",
        "40": "打捞堆",
        "41": "资源堆",
        "42": "圣物",
        "43": "带着圣物的僧侣",
        "44": "火枪手",
        "45": "双手剑士",
        "46": "长枪兵",
        "47": "侦察",
        "48": "矿场",
        "49": "农田",
        "50": "长矛兵",
        "51": "组装的单位",
        "52": "箭塔",
        "53": "登船",
        "54": "拆装的攻城单位",
        "55": "弩炮",
        "56": "突袭者",
        "57": "骑兵突袭者",
        "58": "牲畜",
        "59": "国王",
        "60": "其他建筑",
        "61": "可控制的动物"
    },
    "datasetObjectType": {
        "-1": "<无>",
        "1": "其他",
        "2": "建筑",
        "3": "平民",
        "4": "军事"
    },
    "datasetObjectState": {
        "-1": "",
        "0": "地基",
        "1": "几乎活着",
        "2": "活着",
        "3": "资源",
        "4": "濒死",
        "5": "死亡",
        "6": "亡灵",
        "7": "删除"
    },
    "datasetDifficultyLevel": {
        "-1": "极限",
        "0": "极难",
        "1": "难",
        "2": "中等",
        "3": "标准",
        "4": "最易"
    },
    "datasetTechnologyState": {
        "-1": "已禁用",
        "0": "未准备好",
        "1": "准备好",
        "2": "正在研究",
        "3": "完成",
        "4": "已队列"
    },
    "datasetComparison": {
        "0": "等于",
        "1": "小于",
        "2": "大于",
        "3": "小于等于",
        "4": "大于等于"
    },
    "datasetDiplomacyState": {
        "0": "联盟",
        "1": "中立",
        "3": "敌对"
    },
    "datasetUnitAIAction": {
        "0": "任何",
        "1": "攻击",
        "2": "自卫",
        "3": "建造",
        "4": "治疗",
        "5": "招降",
        "6": "探索",
        "7": "停止",
        "8": "逃亡",
        "9": "撤退",
        "10": "采集",
        "11": "移动",
        "12": "巡逻",
        "13": "跟随",
        "14": "狩猎",
        "15": "运输",
        "16": "贸易",
        "17": "躲避",
        "18": "进入",
        "19": "修理",
        "20": "训练",
        "21": "研究",
        "22": "卸下",
        "23": "圣物",
        "24": "闲置",
        "25": "前往触发器"
    },
    "datasetVictoryTimerType": {
        "0": "世界奇观定时器",
        "1": "圣物定时器",
        "2": "占山为王定时器"
    },
    "datasetDecisionOption": {
        "0": "任意",
        "1": "选项 1",
        "2": "选项 2"
    },
    "datasetActionType": {
        "-1": "默认行动",
        "0": "行动",
        "1": "移动",
        "2": "巡逻",
        "3": "警卫",
        "4": "跟随",
        "5": "停止",
        "6": "攻击特定范围",
        "7": "驻扎",
        "8": "击杀",
        "9": "卸下",
        "10": "聚集点",
        "11": "锁上/开启",
        "12": "工作",
        "13": "取消驻扎",
        "14": "放下圣物",
        "15": "组装",
        "16": "拆装",
        "17": "移动攻击",
        "18": "横列阵形",
        "19": "方阵阵形",
        "20": "交错阵形",
        "21": "侧翼阵形"
    },
    "datasetOperation": {
        "-1": "增加",
        "0": "<0>",
        "1": "设置",
        "2": "增加",
        "3": "减去",
        "4": "乘以",
        "5": "除以"
    },
    "datasetDamageClass": {
        "-1": "<-1>",
        "0": "<0>",
        "1": "步兵",
        "2": "重战船",
        "3": "远程",
        "4": "近战",
        "5": "象",
        "6": "<6>",
        "7": "<7>",
        "8": "骑兵",
        "9": "<9>",
        "10": "<10>",
        "11": "建筑",
        "12": "<12>",
        "13": "防御建筑",
        "14": "掠食猛兽",
        "15": "弓兵",
        "16": "船舰",
        "17": "攻城车",
        "18": "树木",
        "19": "特色单位",
        "20": "器材",
        "21": "标准建筑",
        "22": "城墙与门",
        "23": "火药单位",
        "24": "食用猛兽",
        "25": "僧侣",
        "26": "城堡",
        "27": "长矛兵",
        "28": "骑射手",
        "29": "冲击步兵",
        "30": "骆驼",
        "31": "<烈堤司>",
        "32": "意大利佣兵",
        "33": "<33>",
        "34": "渔船",
        "35": "马穆鲁克",
        "36": "英雄和国王",
        "37": "重型器材",
        "38": "掷矛手",
        "39": "<龙脉>",
        "40": "房屋",
        "41": "<41>",
        "42": "<42>",
        "43": "<43>",
        "44": "<44>",
        "45": "<45>",
        "46": "<46>",
        "47": "<47>",
        "48": "<48>",
        "49": "<49>"
    },
    "datasetAttackStance": {
        "-1": "<-1>",
        "0": "攻击姿态",
        "1": "防御姿态",
        "2": "站岗姿态",
        "3": "不攻击姿态"
    },
    "datasetVisibilityState": {
        "-1": "<-1>",
        "0": "可见",
        "1": "不可见",
        "2": "已探索"
    },
    "datasetPlayerColorId": {
        "-1": "<-1>",
        "0": "蓝色",
        "1": "红色",
        "2": "绿色",
        "3": "黄色",
        "4": "青色",
        "5": "紫色",
        "6": "灰色",
        "7": "橙色"
    },
    "dataUnitFaceToName": {
        "-1": "<-1>",
        "0": "东",
        "1": "东偏南",
        "2": "东南",
        "3": "南偏东",
        "4": "南",
        "5": "南偏西",
        "6": "西南",
        "7": "西偏南",
        "8": "西",
        "9": "西偏北",
        "10": "西北",
        "11": "北偏西",
        "12": "北",
        "13": "北偏东",
        "14": "东北",
        "15": "东偏北"
    },
    "datasetColorMood": {
        "0": "空白",
        "1": "秋天",
        "2": "冬天",
        "3": "丛林",
        "4": "沙漠",
        "5": "夜晚",
        "6": "夜间",
        "7": "春季",
        "8": "稀树草原",
        "9": "北极",
        "10": "雨林",
        "11": "湿地",
        "12": "草原",
        "13": "薄雾",
        "14": "夏季",
        "15": "昏暗",
        "16": "寒冷多雾",
        "17": "黄昏",
        "18": "黑暗"
    },
    "datasetTimeUnit": {
        "0": "年",
        "1": "分钟",
        "2": "秒",
        "3": "分钟和秒"
    },
    "datasetObjectAttribute": {
        "0": "生命值",
        "1": "视野",
        "2": "驻扎容量",
        "3": "单位尺寸 X",
        "4": "单位尺寸 Y",
        "5": "移动速度",
        "6": "旋转速度",
        "7": "未使用的",
        "8": "护甲",
        "9": "攻击力",
        "10": "攻击重新加载时间",
        "11": "准确度百分比",
        "12": "最大射程",
        "13": "工作效率",
        "14": "运载量",
        "15": "基础护甲",
        "16": "炮弹单位",
        "17": "建筑图标覆盖",
        "18": "地形防御奖励",
        "19": "炮弹智能模式",
        "20": "最小射程",
        "21": "资源储备",
        "22": "爆炸广度",
        "23": "搜索半径",
        "24": "额外伤害抗性",
        "25": "图标 ID",
        "26": "第二资源仓库储备量",
        "27": "第三资源仓库储备量",
        "28": "迷雾能见度",
        "29": "遮挡模式",
        "30": "驻扎类型",
        "32": "单位尺寸 Z",
        "33": "可以建在",
        "34": "基础地形",
        "40": "英雄状态",
        "41": "帧延迟",
        "42": "训练位置",
        "43": "训练按钮",
        "44": "爆炸攻击等级",
        "45": "爆炸防御等级",
        "46": "显示攻击力",
        "47": "显示射程",
        "48": "显示近战护甲",
        "49": "显示远程护甲",
        "50": "物体名称 ID",
        "51": "简短描述 ID",
        "53": "地形限制 ID",
        "54": "单位特征",
        "56": "特征部分",
        "57": "死亡单位 ID",
        "58": "热键 ID",
        "59": "最大蓄力",
        "60": "回复速度",
        "61": "蓄力事件",
        "62": "蓄力类型",
        "63": "作战能力",
        "64": "攻击散布",
        "65": "次要炮弹单位",
        "66": "血迹单位",
        "67": "炮弹命中模式",
        "68": "炮弹消失模式",
        "69": "炮弹弧线",
        "70": "攻击力图示",
        "71": "站立图示",
        "72": "站立图示 2",
        "73": "濒死图示",
        "74": "亡灵图示",
        "75": "行走图示",
        "76": "奔跑图示",
        "77": "特殊图示",
        "78": "障碍类型",
        "79": "阻挡等级",
        "80": "选择效果",
        "100": "资源费用",
        "101": "训练时间",
        "102": "投射单位总数",
        "103": "食物费用",
        "104": "木材费用",
        "105": "黄金费用",
        "106": "石料费用",
        "107": "投射单位最大总数",
        "108": "驻扎治疗率",
        "109": "恢复率",
        "110": "人口",
        "111": "最小招降时间修改器",
        "112": "最大招降时间修改器",
        "113": "招降几率修改器",
        "114": "阵形类别",
        "115": "区域伤害",
        "118": "伤害反弹",
        "119": "友军火焰伤害",
        "120": "生命值恢复百分比",
        "121": "能力按钮图标 ID",
        "122": "能力短工具提示 ID",
        "123": "能力长工具提示 ID",
        "124": "能力热键操作",
        "125": "装填弹药单位",
        "126": "可用单位旗帜",
        "127": "禁用单位旗帜",
        "128": "攻击优先级",
        "129": "无敌等级",
        "130": "驻扎火力",
        "131": "攻击图示 2"
    }
}